juntagrico_badges/__init__.py
juntagrico_badges/admin.py
juntagrico_badges/apps.py
juntagrico_badges/urls.py
juntagrico_badges/views.py
juntagrico_badges/views_admin.py
juntagrico_badges/entity/__init__.py
juntagrico_badges/entity/badges.py
juntagrico_badges/migrations/0001_initial.py
juntagrico_badges/migrations/__init__.py
juntagrico_badges/templates/jbg/home.html
juntagrico_badges/templates/jbg/management_lists/badges.html
juntagrico_badges/templates/jbg/snippets/badge.html
juntagrico_badges/templates/juntagrico/menu/admin.html
juntagrico_badges/templates/juntagrico/menu/user.html
juntagrico_badges/tests/__init__.py
juntagrico_badges/tests/test_badges.py
juntagrico_badges-1.7.0.dist-info/licenses/LICENSE
juntagrico_badges-1.7.0.dist-info/METADATA
juntagrico_badges-1.7.0.dist-info/WHEEL
juntagrico_badges-1.7.0.dist-info/top_level.txt
juntagrico_badges-1.7.0.dist-info/RECORD
